[
    {
        "name": "Lever-Crystal_Peak_Spike_Grub",
        "logic": "ORIG | ((Mines_03[bot1] | Mines_03[right1]) + BLUEMOTH + (((CRYSTALMASTER | LEFTDASH | AIRSTALL) + SPIKETUNNELS) | Lever-Crystal_Peak_Spike_Grub)) | (Mines_03[bot1] + ANTIGRAV + (PRECISEMOVEMENT | Longnail | Mark_of_Pride) + SPIKETUNNELS) | (Mines_03[right1] + ANTIGRAV + SPIKETUNNELS)"
    },
    {
        "name": "Lever-Crystal_Peak_Crushers_Grub",
        "logic": "ORIG | ((Mines_19[left1] | Mines_19[right1]) + (ANTIGRAV | BLUEMOTH) + (LEFTDASH | CRYSTALMASTER | Lever-Crystal_Peak_Crushers_Grub))"
    },
    {
        "name": "Lever-Crystal_Peak_Crushers_Chest",
        "logic": "ORIG | (Mines_37[bot1] + ANTIGRAVWINGS)"
    },
    {
        "name": "Lever-Crystal_Peak_Above_Chest",
        "logic": "ORIG | (Mines_37[top1] + ANTIGRAVWINGS) | (Mines_37[bot1] + ANTIGRAVWINGS + ($TrueOrNotExist[Lever-Crystal_Peak_Crushers_Chest] | FULLDASH | (DASHSPRINT + OBSCURESKIPS)))"
    },
    {
        "name": "Bench-Gardens_Cornifer",
        "logic": "ORIG | (Fungus1_24[left1] + (ANTIGRAV | BLUEMOTH))"
    },
    {
        "name": "Switch-Petra_Arena",
        "logic": "ORIG | ((Fungus3_05[left1] | Fungus3_05[right1] | (Fungus3_05[right2] + Switch-Petra_Arena)) + (ANTIGRAVWINGS | CRYSTALMASTER | (ANTIGRAV + LEFTCLAW + PRECISEMOVEMENT) | (ANTIGRAV + RIGHTDASH) | (ANTIGRAV + RIGHTSUPERDASH) | (ANTIGRAV + AIRSTALL + ROOMSOUL)))"
    },
    {
        "name": "Bench-Gardens_Stag",
        "logic": "ORIG | (Fungus3_40[top1] + (ANTIGRAV | BLUEMOTH | CRYSTALMASTER))"
    },
    {
        "name": "Lever-Below_Overgrown_Mound",
        "logic": "ORIG | (Fungus3_44[bot1] + (ANTIGRAV | BLUEMOTH))"
    },
    {
        "name": "Bench-Canyon_Depths",
        "logic": "ORIG | (Fungus3_26[right1] + (ANTIGRAV | BLUEMOTH | CRYSTALMASTER))"
    },
    {
        "name": "Bench-Archives",
        "logic": "ORIG | (Fungus3_archive[bot1] + (ANTIGRAV | BLUEMOTH))"
    },
    {
        "name": "Lever-Queen's_Station_Mask_Shard",
        "logic": "ORIG | (Fungus2_01 + (BLUEMOTH | YEET | (ANTIGRAV + LEFTDASH) | (ANTIGRAV + GREATSLASH) | (ANTIGRAV + AIRSTALL + AREASOUL) | (ANTIGRAV + RIGHTCLAW + LEFTSUPERDASH) | (CRYSTALMASTER + FULLCLAW)))"
    },
    {
        "name": "Lever-Fungal_Wastes_Bouncy_Grub",
        "logic": "ORIG | (Fungus2_18[right1] + (ANTIGRAV | BLUEMOTH | CRYSTALMASTER))"
    },
    {
        "name": "Lever-Fungal_Wastes_Thorns_Gauntlet",
        "logic": "ORIG | (Fungus2_04 + (BLUEMOTH | (CRYSTALMASTER + RIGHTCLAW)))"
    },
    {
        "name": "Lever-Pilgrim's_Way_Left",
        "logic": "ORIG | (Fungus2_21[left1] + (ANTIGRAVWINGS | (ANTIGRAV + RIGHTCLAW + GREATSLASH) | (ANTIGRAV + RIGHTCLAW + AIRSTALL + ROOMSOUL) | (CRYSTALMASTER + RIGHTCLAW) | (CRYSTALMASTER + GREATSLASH + WINGS) | (CRYSTALMASTER + AIRSTALL + ROOMSOUL + WINGS) | (CRYSTALMASTER + RIGHTDASH + WINGS))) | (Fungus2_21[right1] + QUAKE + (ANTIGRAVWINGS | (CRYSTALMASTER + FULLCLAW)))"
    },
    {
        "name": "Lever-Pilgrim's_Way_Right",
        "logic": "ORIG | (Fungus2_21[left1] + (ANTIGRAVWINGS | (ANTIGRAV + RIGHTCLAW + GREATSLASH) | (ANTIGRAV + RIGHTCLAW + AIRSTALL + ROOMSOUL) | (CRYSTALMASTER + RIGHTCLAW) | (CRYSTALMASTER + GREATSLASH + WINGS) | (CRYSTALMASTER + AIRSTALL + ROOMSOUL + WINGS) | (CRYSTALMASTER + RIGHTDASH + WINGS))) | (Fungus2_21[right1] + QUAKE + (ANTIGRAVWINGS | (ANTIGRAV + ANYCLAW)))"
    },
    {
        "name": "Bench-Bretta",
        "logic": "ORIG | ((Fungus2_13 | Fungus2_13[left3]) + (ANTIGRAV | BLUEMOTH | CRYSTALMASTER))"
    },
    {
        "name": "Lever-Mantis_Lords_Access",
        "logic": "ORIG | (Fungus2_14 + (ANTIGRAVWINGS | (ANTIGRAV + ANYCLAW) | (CRYSTALMASTER + LEFTCLAW)))"
    },
    {
        "name": "Lever-Mantis_Lords_Top_Left",
        "logic": "ORIG | (Fungus2_15[top3] + (ANTIGRAV | BLUEMOTH)) | (Fungus2_15[right1] + (ANTIGRAVWINGS | (ANTIGRAV + ANYCLAW) | (ANTIGRAV + $TrueOrNotExist[Lever-Mantis_Lords_Middle_Right]))) | (Fungus2_15[left1] + (BLUEMOTH | (YEET + LEFTCLAW + WINGS)))"
    },
    {
        "name": "Lever-Mantis_Lords_Middle_Left",
        "logic": "ORIG | (Fungus2_15[left1] + (BLUEMOTH | (YEET + LEFTCLAW + WINGS)))"
    },
    {
        "name": "Lever-Mantis_Lords_Bottom_Left",
        "logic": "ORIG | (Fungus2_15[left1] + (BLUEMOTH | (YEET + LEFTCLAW + WINGS)))"
    },
    {
        "name": "Lever-Mantis_Lords_Middle_Right",
        "logic": "ORIG | (Fungus2_15[left1] + (BLUEMOTH | (YEET + LEFTCLAW + WINGS))) | (Fungus2_15[top3] + ANTIGRAVWINGS)"
    },
    {
        "name": "Lever-Mantis_Lords_Bottom_Right",
        "logic": "ORIG | (Fungus2_15[left1] + (BLUEMOTH | (YEET + LEFTCLAW + WINGS))) | (Fungus2_15[top3] + ANTIGRAVWINGS) | (Fungus2_15[right1] + (ANTIGRAVWINGS | (ANTIGRAV + ANYCLAW)))"
    },
    {
        "name": "Lever-City_Above_Lemm_Upper",
        "logic": "ORIG | (Ruins1_05[bot2] + BLUEMOTH + Lever-City_Above_Lemm_Upper) | (Ruins1_05[bot1] + Lever-City_Above_Lemm_Upper + (ANTIGRAVWINGS | (ANTIGRAV + ANYCLAW) | (SNAILSLASH + Longnail + Mark_of_Pride + BACKGROUNDPOGOS)))"
    },
    {
        "name": "Lever-City_Above_Lemm_Left",
        "logic": "ORIG | ((Ruins1_05c[top1] | Ruins1_05c[top3] | Ruins1_05c) + $TrueAndExists[Lever-City_Above_Lemm_Left] + (ANTIGRAV | BLUEMOTH))"
    },
    {
        "name": "Lever-Sanctum_Soul_Warrior",
        "logic": "ORIG | (Ruins1_23 + (ANTIGRAV | BLUEMOTH | (CRYSTALMASTER + RIGHTCLAW + AIRSTALL + ROOMSOUL)))"
    },
    {
        "name": "Lever-Sanctum_Bottom",
        "logic": "ORIG | (Ruins1_23 + $TrueAndExists[Lever-Sanctum_Bottom] + (ANTIGRAV | BLUEMOTH))"
    },
    {
        "name": "Lever-Sanctum_East",
        "logic": "ORIG | ((Ruins1_25[left1] | Ruins1_25[left2] | Ruins1_25[left3]) + (ANTIGRAV | BLUEMOTH))"
    },
    {
        "name": "Lever-Below_Spell_Twister",
        "logic": "ORIG | (Ruins1_30 + (ANTIGRAV | BLUEMOTH))"
    },
    {
        "name": "Lever-Sanctum_West_Upper",
        "logic": "ORIG | (Ruins1_32[right1] + ANTIGRAVWINGS + QUAKE + ROOMSOUL)"
    },
    {
        "name": "Lever-Sanctum_West_Lower",
        "logic": "ORIG | (Ruins1_32[right1] + (ANTIGRAVWINGS | (SNAILSLASH + Lever-Sanctum_West_Upper)) + QUAKE + ROOMSOUL)"
    },
    {
        "name": "Lever-City_Fountain",
        "logic": "ORIG | (Ruins1_27[left1] + (ANTIGRAVWINGS | (ANTIGRAV + RIGHTCLAW)))"
    },
    {
        "name": "Lever-Emilitia",
        "logic": "ORIG | (Ruins_House_03[left2] + BLUEMOTH)"
    },
    {
        "name": "Mr_Mushroom-Kingdom's_Edge",
        "logic": "ORIG | (Deepnest_East_01[bot1] + Spore_Shroom + (MRMUSHROOMFOUND>1 | (MRMUSHROOMFOUND>0 + DREAMER3)) + (ANTIGRAV | BLUEMOTH))"
    },
    {
        "name": "Bench-Bardoon",
        "logic": "ORIG | ((Deepnest_East_04 | Bench-Bardoon's_Tail) + (ANTIGRAV | BLUEMOTH))"
    },
    {
        "name": "Bench-Bardoon's_Tail",
        "logic": "ORIG | (Deepnest_East_04 + (ANTIGRAV | BLUEMOTH))"
    },
    {
        "name": "Bench-Beast's_Den",
        "logic": "ORIG | (Deepnest_Spider_Town[left1] + (ANTIGRAVWINGS | (ANTIGRAV + ANYCLAW)))"
    },
    {
        "name": "Bench-Galien's_Grave",
        "logic": "ORIG | (Deepnest_40[right1] + (ANTIGRAVWINGS | (ANTIGRAV + ANYCLAW)))"
    },
    {
        "name": "Lever-Failed_Tramway_Right",
        "logic": "ORIG | (Deepnest_26 + (ANTIGRAVWINGS | (ANTIGRAV + ENEMYPOGOS) | SNAILSLASH))"
    },
    {
        "name": "Lever-Failed_Tramway_Left",
        "logic": "ORIG | (Deepnest_26b[right2] + (ANTIGRAV | BLUEMOTH | SNAILSLASH | (CRYSTALMASTER + ENEMYPOGOS) | (CRYSTALMASTER + LEFTCLAW))) | ($TrueAndExists[Bench-Destroyed_Tram] + (ANTIGRAV | BLUEMOTH | (CRYSTALMASTER + ENEMYPOGOS) | (CRYSTALMASTER + WINGS)))"
    },

    // move these to LogicPatches later
    {
        "name": "Broke_Camp_Bench_Wall",
        "logic": "ORIG | ((Deepnest_East_11[right1] | Deepnest_East_11[left1] | Deepnest_East_11[bot1]) + (ANTIGRAV | BLUEMOTH) + UPWALLBREAK)"
    }
]